templated/__init__.py
templated/__main__.py
templated/_utils/chat2vanilla_lm.py
templated/_utils/llms.py
templated/function.py
templated/templates/__old_template.py
templated/templates/base_template.py
templated/templates/fstring_template.py
templated/templates/jinja_template.py
templated-0.1.2.dist-info/LICENSE
templated-0.1.2.dist-info/METADATA
templated-0.1.2.dist-info/WHEEL
templated-0.1.2.dist-info/RECORD
