Metadata-Version: 2.1
Name: templated
Version: 0.1.2
Summary: 
Author: Jacob Valdez
Author-email: jacob.valdez@limboid.ai
Requires-Python: >=3.10,<4.0
Classifier: Programming Language :: Python :: 3
Classifier: Programming Language :: Python :: 3.10
Classifier: Programming Language :: Python :: 3.11
Requires-Dist: jinja2 (>=3.1.2,<4.0.0)
Requires-Dist: langchain (>=0.0.152,<0.0.153)
Requires-Dist: openai[openai] (>=0.27.5,<0.28.0)
Requires-Dist: python-exports (>=1.0.0,<2.0.0)
